dbt/__init__.py
dbt/adapters/database/__init__.py
dbt/adapters/database/__version__.py
dbt/adapters/database/column.py
dbt/adapters/database/connections.py
dbt/adapters/database/impl.py
dbt/adapters/database/relation.py
dbt/include/database/__init__.py
dbt/include/database/dbt_project.yml
dbt/include/database/profile_template.yml
dbt/include/database/sample_profiles.yml
dbt/include/database/macros/adapters/metadata.sql
dbt_database-0.1.5.dist-info/METADATA
dbt_database-0.1.5.dist-info/WHEEL
dbt_database-0.1.5.dist-info/RECORD
