Metadata-Version: 2.4
Name: dbt-database
Version: 0.1.5
Summary: The custom adapter plugin for dbt
Project-URL: Homepage, https://github.com/dbt-labs/dbt-adapters/tree/main/dbt-database
Project-URL: Documentation, https://docs.getdbt.com
Project-URL: Repository, https://github.com/dbt-labs/dbt-adapters.git#subdirectory=dbt-database
Project-URL: Issues, https://github.com/dbt-labs/dbt-adapters/issues
Project-URL: Changelog, https://github.com/dbt-labs/dbt-adapters/blob/main/dbt-database/CHANGELOG.md
Author-email: dbt Labs <info@dbtlabs.com>
Maintainer-email: dbt Labs <info@dbtlabs.com>
Keywords: adapter,adapters,database,dbt,dbt Cloud,dbt Core,dbt Labs,dbt-core,elt
Classifier: Development Status :: 5 - Production/Stable
Classifier: License :: OSI Approved :: Apache Software License
Classifier: Operating System :: MacOS :: MacOS X
Classifier: Operating System :: Microsoft :: Windows
Classifier: Operating System :: POSIX :: Linux
Classifier: Programming Language :: Python :: 3.9
Classifier: Programming Language :: Python :: 3.10
Classifier: Programming Language :: Python :: 3.11
Classifier: Programming Language :: Python :: 3.12
Requires-Python: >=3.9.0
Requires-Dist: dbt-adapters<2.0,>=1.0
Requires-Dist: dbt-common<2.0,>=1.0
Requires-Dist: dbt-core>=1.0
Requires-Dist: mysql-connector-python>=8.0
